chat_file/__init__.py
chat_file/chat_file.py
chat_file-0.0.1.dist-info/LICENSE
chat_file-0.0.1.dist-info/METADATA
chat_file-0.0.1.dist-info/WHEEL
chat_file-0.0.1.dist-info/top_level.txt
chat_file-0.0.1.dist-info/RECORD
